data/__init__.py
data/dsf/__init__.py
data/fundq/__init__.py
data/msf/__init__.py
doc/__init__.py
ksif/__init__.py
ksif/core/__init__.py
ksif/core/columns.py
ksif/core/frame.py
ksif/core/outcomes.py
ksif/errors/__init__.py
ksif/io/__init__.py
ksif/io/downloader.py
ksif/io/google_drive.py
ksif/tests/__init__.py
ksif/tests/frame/__init__.py
ksif/tests/frame/test_benchmark.py
ksif/tests/frame/test_get_returns.py
ksif/tests/frame/test_outcome.py
ksif/tests/frame/test_periodic_percentage.py
ksif/tests/frame/test_periodic_rank.py
ksif/tests/frame/test_periodic_standardize.py
ksif/tests/frame/test_quantile_distribution_ratio.py
ksif/tests/frame/test_rank_correlation.py
ksif/tests/frame/test_show_plot.py
ksif/tests/util/__init__.py
ksif/tests/util/test_checker.py
ksif/util/__init__.py
ksif/util/checker.py
ksif/util/memoization.py
ksif/util/retrial.py
ksif/util/spinner.py
ksif_tech_pocket/__init__.py
ksif_tech_pocket/pocket.py
ksif_tech_pocket/record.py
ksif_tech_pocket/test.py
ksif_tech_pocket/util.py
ksif_tech_pocket/data/__init__.py
ksif_tech_pocket/data/_util.py
ksif_tech_pocket/data/price.py
ksif-20200402.post2.dist-info/LICENSE
ksif-20200402.post2.dist-info/METADATA
ksif-20200402.post2.dist-info/WHEEL
ksif-20200402.post2.dist-info/top_level.txt
ksif-20200402.post2.dist-info/RECORD
