Metadata-Version: 2.1
Name: ksif
Version: v20200402-02
Summary: Quantitative investment tools for KSIF
Home-page: https://github.com/sangheumcho/ksif
Author: KSIF Tech
Author-email: sh.cho@kaist.ac.kr
License: UNKNOWN
Keywords: ksif,portfolio,backtest,finance
Platform: UNKNOWN
Classifier: Programming Language :: Python :: 3
Classifier: License :: OSI Approved :: MIT License
Classifier: Operating System :: OS Independent
Requires-Python: >=3.5
Requires-Dist: pandas
Requires-Dist: numpy
Requires-Dist: matplotlib
Requires-Dist: scikit-learn
Requires-Dist: scipy
Requires-Dist: statsmodels
Requires-Dist: patsy
Requires-Dist: performanceanalytics
Requires-Dist: tqdm
Requires-Dist: requests
Requires-Dist: tables
Requires-Dist: python-dateutil
Requires-Dist: urllib3
Requires-Dist: xlrd
